Metadata-Version: 2.1
Name: Python123ETO
Version: 1.0.3
Summary: A small example package
Home-page: https://github.com/ETO-QSH
Author: ETO
Author-email: 2373204754@qq.com
License: AGPL-3.0 License
Platform: all
Classifier: Development Status :: 1 - Planning 
License-File: LICENSE.txt
